{"algorithm": "DeepProbLog", "seed": 0, "method": "exact", "nb_epochs": 3, "batch_size": 8, "learning_rate": 0.001, "use_dropout": false, "size_val": 0.1, "accuracy": 0.9474, "training_time": 2653.201404809952, "testing_time": 561.5875401496887, "model_file": "label_noise_0.5/DeepProbLog_final_0_exact_100_8_0.001_False_0.1"}
{"algorithm": "DeepProbLog", "seed": 1, "method": "exact", "nb_epochs": 3, "batch_size": 8, "learning_rate": 0.001, "use_dropout": false, "size_val": 0.1, "accuracy": 0.958, "training_time": 2641.64098238945, "testing_time": 565.4618737697601, "model_file": "label_noise_0.5/DeepProbLog_final_1_exact_100_8_0.001_False_0.1"}
{"algorithm": "DeepProbLog", "seed": 2, "method": "exact", "nb_epochs": 3, "batch_size": 8, "learning_rate": 0.001, "use_dropout": false, "size_val": 0.1, "accuracy": 0.9522, "training_time": 2638.439454317093, "testing_time": 562.53422498703, "model_file": "label_noise_0.5/DeepProbLog_final_2_exact_100_8_0.001_False_0.1"}
{"algorithm": "DeepProbLog", "seed": 3, "method": "exact", "nb_epochs": 6, "batch_size": 8, "learning_rate": 0.001, "use_dropout": false, "size_val": 0.1, "accuracy": 0.944, "training_time": 3947.7022445201874, "testing_time": 563.2640895843506, "model_file": "label_noise_0.5/DeepProbLog_final_3_exact_100_8_0.001_False_0.1"}
{"algorithm": "DeepProbLog", "seed": 4, "method": "exact", "nb_epochs": 4, "batch_size": 8, "learning_rate": 0.001, "use_dropout": false, "size_val": 0.1, "accuracy": 0.956, "training_time": 3084.7288641929626, "testing_time": 563.1711299419403, "model_file": "label_noise_0.5/DeepProbLog_final_4_exact_100_8_0.001_False_0.1"}
{"algorithm": "DeepProbLog", "seed": 5, "method": "exact", "nb_epochs": 2, "batch_size": 8, "learning_rate": 0.001, "use_dropout": false, "size_val": 0.1, "accuracy": 0.9502, "training_time": 2182.23482465744, "testing_time": 562.0750517845154, "model_file": "label_noise_0.5/DeepProbLog_final_5_exact_100_8_0.001_False_0.1"}
{"algorithm": "DeepProbLog", "seed": 6, "method": "exact", "nb_epochs": 3, "batch_size": 8, "learning_rate": 0.001, "use_dropout": false, "size_val": 0.1, "accuracy": 0.9546, "training_time": 2639.4578540325165, "testing_time": 567.311945438385, "model_file": "label_noise_0.5/DeepProbLog_final_6_exact_100_8_0.001_False_0.1"}
{"algorithm": "DeepProbLog", "seed": 7, "method": "exact", "nb_epochs": 3, "batch_size": 8, "learning_rate": 0.001, "use_dropout": false, "size_val": 0.1, "accuracy": 0.9552, "training_time": 2657.26371216774, "testing_time": 562.6055428981781, "model_file": "label_noise_0.5/DeepProbLog_final_7_exact_100_8_0.001_False_0.1"}
{"algorithm": "DeepProbLog", "seed": 8, "method": "exact", "nb_epochs": 4, "batch_size": 8, "learning_rate": 0.001, "use_dropout": false, "size_val": 0.1, "accuracy": 0.9492, "training_time": 3074.0649638175964, "testing_time": 565.9683310985565, "model_file": "label_noise_0.5/DeepProbLog_final_8_exact_100_8_0.001_False_0.1"}
{"algorithm": "DeepProbLog", "seed": 9, "method": "exact", "nb_epochs": 4, "batch_size": 8, "learning_rate": 0.001, "use_dropout": false, "size_val": 0.1, "accuracy": 0.942, "training_time": 3091.9844098091125, "testing_time": 568.7177641391754, "model_file": "label_noise_0.5/DeepProbLog_final_9_exact_100_8_0.001_False_0.1"}
