{"algorithm": "NN", "seed": 0, "nb_epochs": 54, "optimizer": "Adam", "batch_size": 128, "learning_rate": 0.001, "dropout_rate": 0.2, "size_val": 0.1, "accuracy": 0.4994, "training_time": 201.13935804367065, "testing_time": 2.5506503582000732, "model_file": "NN_final_0_0_100_Adam_128_0.001_0.2_0.1"}
{"algorithm": "NN", "seed": 1, "nb_epochs": 44, "optimizer": "Adam", "batch_size": 128, "learning_rate": 0.001, "dropout_rate": 0.2, "size_val": 0.1, "accuracy": 0.478, "training_time": 171.11776852607727, "testing_time": 2.861889600753784, "model_file": "NN_final_1_0_100_Adam_128_0.001_0.2_0.1"}
