{"algorithm": "LTN", "seed": 0, "nb_epochs": 5, "batch_size": 8, "learning_rate": 0.001, "p_forall": 1, "p_exists": 1, "dropout_rate": 0, "size_val": 0.1, "accuracy": 0.5076666474342346, "model_file": "LTN_param_0_100_8_0.001_1_1_0_0.1"}
{"algorithm": "LTN", "seed": 0, "nb_epochs": 12, "batch_size": 32, "learning_rate": 0.001, "p_forall": 1, "p_exists": 1, "dropout_rate": 0, "size_val": 0.1, "accuracy": 0.9670000076293945, "model_file": "LTN_param_0_100_32_0.001_1_1_0_0.1"}
{"algorithm": "LTN", "seed": 0, "nb_epochs": 14, "batch_size": 128, "learning_rate": 0.001, "p_forall": 1, "p_exists": 1, "dropout_rate": 0, "size_val": 0.1, "accuracy": 0.8119999766349792, "model_file": "LTN_param_0_100_128_0.001_1_1_0_0.1"}
{"algorithm": "LTN", "seed": 0, "nb_epochs": 33, "batch_size": 512, "learning_rate": 0.001, "p_forall": 1, "p_exists": 1, "dropout_rate": 0, "size_val": 0.1, "accuracy": 0.6579999923706055, "model_file": "LTN_param_0_100_512_0.001_1_1_0_0.1"}
{"algorithm": "LTN", "seed": 0, "nb_epochs": 1, "batch_size": 8, "learning_rate": 0.001, "p_forall": 1, "p_exists": 2, "dropout_rate": 0, "size_val": 0.1, "accuracy": 0.0989999994635582, "model_file": "LTN_param_0_100_8_0.001_1_2_0_0.1"}
{"algorithm": "LTN", "seed": 0, "nb_epochs": 1, "batch_size": 32, "learning_rate": 0.001, "p_forall": 1, "p_exists": 2, "dropout_rate": 0, "size_val": 0.1, "accuracy": 0.0989999994635582, "model_file": "LTN_param_0_100_32_0.001_1_2_0_0.1"}
{"algorithm": "LTN", "seed": 0, "nb_epochs": 1, "batch_size": 128, "learning_rate": 0.001, "p_forall": 1, "p_exists": 2, "dropout_rate": 0, "size_val": 0.1, "accuracy": 0.0989999994635582, "model_file": "LTN_param_0_100_128_0.001_1_2_0_0.1"}
{"algorithm": "LTN", "seed": 0, "nb_epochs": 1, "batch_size": 512, "learning_rate": 0.001, "p_forall": 1, "p_exists": 2, "dropout_rate": 0, "size_val": 0.1, "accuracy": 0.0989999994635582, "model_file": "LTN_param_0_100_512_0.001_1_2_0_0.1"}
{"algorithm": "LTN", "seed": 0, "nb_epochs": 3, "batch_size": 8, "learning_rate": 0.001, "p_forall": 2, "p_exists": 1, "dropout_rate": 0, "size_val": 0.1, "accuracy": 0.6136666536331177, "model_file": "LTN_param_0_100_8_0.001_2_1_0_0.1"}
{"algorithm": "LTN", "seed": 0, "nb_epochs": 14, "batch_size": 32, "learning_rate": 0.001, "p_forall": 2, "p_exists": 1, "dropout_rate": 0, "size_val": 0.1, "accuracy": 0.968999981880188, "model_file": "LTN_param_0_100_32_0.001_2_1_0_0.1"}
{"algorithm": "LTN", "seed": 0, "nb_epochs": 13, "batch_size": 128, "learning_rate": 0.001, "p_forall": 2, "p_exists": 1, "dropout_rate": 0, "size_val": 0.1, "accuracy": 0.653333306312561, "model_file": "LTN_param_0_100_128_0.001_2_1_0_0.1"}
{"algorithm": "LTN", "seed": 0, "nb_epochs": 19, "batch_size": 512, "learning_rate": 0.001, "p_forall": 2, "p_exists": 1, "dropout_rate": 0, "size_val": 0.1, "accuracy": 0.6510000228881836, "model_file": "LTN_param_0_100_512_0.001_2_1_0_0.1"}
{"algorithm": "LTN", "seed": 0, "nb_epochs": 1, "batch_size": 8, "learning_rate": 0.001, "p_forall": 2, "p_exists": 2, "dropout_rate": 0, "size_val": 0.1, "accuracy": 0.0989999994635582, "model_file": "LTN_param_0_100_8_0.001_2_2_0_0.1"}
{"algorithm": "LTN", "seed": 0, "nb_epochs": 1, "batch_size": 32, "learning_rate": 0.001, "p_forall": 2, "p_exists": 2, "dropout_rate": 0, "size_val": 0.1, "accuracy": 0.0989999994635582, "model_file": "LTN_param_0_100_32_0.001_2_2_0_0.1"}
{"algorithm": "LTN", "seed": 0, "nb_epochs": 1, "batch_size": 128, "learning_rate": 0.001, "p_forall": 2, "p_exists": 2, "dropout_rate": 0, "size_val": 0.1, "accuracy": 0.0989999994635582, "model_file": "LTN_param_0_100_128_0.001_2_2_0_0.1"}
{"algorithm": "LTN", "seed": 0, "nb_epochs": 1, "batch_size": 512, "learning_rate": 0.001, "p_forall": 2, "p_exists": 2, "dropout_rate": 0, "size_val": 0.1, "accuracy": 0.0989999994635582, "model_file": "LTN_param_0_100_512_0.001_2_2_0_0.1"}
{"algorithm": "LTN", "seed": 0, "nb_epochs": 1, "batch_size": 8, "learning_rate": 0.001, "p_forall": 1, "p_exists": 1, "dropout_rate": 0.2, "size_val": 0.1, "accuracy": 0.052000001072883606, "model_file": "LTN_param_0_100_8_0.001_1_1_0.2_0.1"}
{"algorithm": "LTN", "seed": 0, "nb_epochs": 14, "batch_size": 32, "learning_rate": 0.001, "p_forall": 1, "p_exists": 1, "dropout_rate": 0.2, "size_val": 0.1, "accuracy": 0.6546666622161865, "model_file": "LTN_param_0_100_32_0.001_1_1_0.2_0.1"}
{"algorithm": "LTN", "seed": 0, "nb_epochs": 25, "batch_size": 128, "learning_rate": 0.001, "p_forall": 1, "p_exists": 1, "dropout_rate": 0.2, "size_val": 0.1, "accuracy": 0.6579999923706055, "model_file": "LTN_param_0_100_128_0.001_1_1_0.2_0.1"}
{"algorithm": "LTN", "seed": 0, "nb_epochs": 29, "batch_size": 512, "learning_rate": 0.001, "p_forall": 1, "p_exists": 1, "dropout_rate": 0.2, "size_val": 0.1, "accuracy": 0.512666642665863, "model_file": "LTN_param_0_100_512_0.001_1_1_0.2_0.1"}
{"algorithm": "LTN", "seed": 0, "nb_epochs": 1, "batch_size": 8, "learning_rate": 0.001, "p_forall": 1, "p_exists": 2, "dropout_rate": 0.2, "size_val": 0.1, "accuracy": 0.0989999994635582, "model_file": "LTN_param_0_100_8_0.001_1_2_0.2_0.1"}
{"algorithm": "LTN", "seed": 0, "nb_epochs": 1, "batch_size": 32, "learning_rate": 0.001, "p_forall": 1, "p_exists": 2, "dropout_rate": 0.2, "size_val": 0.1, "accuracy": 0.0989999994635582, "model_file": "LTN_param_0_100_32_0.001_1_2_0.2_0.1"}
{"algorithm": "LTN", "seed": 0, "nb_epochs": 1, "batch_size": 128, "learning_rate": 0.001, "p_forall": 1, "p_exists": 2, "dropout_rate": 0.2, "size_val": 0.1, "accuracy": 0.0989999994635582, "model_file": "LTN_param_0_100_128_0.001_1_2_0.2_0.1"}
{"algorithm": "LTN", "seed": 0, "nb_epochs": 1, "batch_size": 512, "learning_rate": 0.001, "p_forall": 1, "p_exists": 2, "dropout_rate": 0.2, "size_val": 0.1, "accuracy": 0.0989999994635582, "model_file": "LTN_param_0_100_512_0.001_1_2_0.2_0.1"}
{"algorithm": "LTN", "seed": 0, "nb_epochs": 4, "batch_size": 8, "learning_rate": 0.001, "p_forall": 2, "p_exists": 1, "dropout_rate": 0.2, "size_val": 0.1, "accuracy": 0.46166667342185974, "model_file": "LTN_param_0_100_8_0.001_2_1_0.2_0.1"}
{"algorithm": "LTN", "seed": 0, "nb_epochs": 19, "batch_size": 32, "learning_rate": 0.001, "p_forall": 2, "p_exists": 1, "dropout_rate": 0.2, "size_val": 0.1, "accuracy": 0.7799999713897705, "model_file": "LTN_param_0_100_32_0.001_2_1_0.2_0.1"}
{"algorithm": "LTN", "seed": 0, "nb_epochs": 16, "batch_size": 128, "learning_rate": 0.001, "p_forall": 2, "p_exists": 1, "dropout_rate": 0.2, "size_val": 0.1, "accuracy": 0.7746666669845581, "model_file": "LTN_param_0_100_128_0.001_2_1_0.2_0.1"}
{"algorithm": "LTN", "seed": 0, "nb_epochs": 15, "batch_size": 512, "learning_rate": 0.001, "p_forall": 2, "p_exists": 1, "dropout_rate": 0.2, "size_val": 0.1, "accuracy": 0.5206666588783264, "model_file": "LTN_param_0_100_512_0.001_2_1_0.2_0.1"}
{"algorithm": "LTN", "seed": 0, "nb_epochs": 1, "batch_size": 8, "learning_rate": 0.001, "p_forall": 2, "p_exists": 2, "dropout_rate": 0.2, "size_val": 0.1, "accuracy": 0.0989999994635582, "model_file": "LTN_param_0_100_8_0.001_2_2_0.2_0.1"}
{"algorithm": "LTN", "seed": 0, "nb_epochs": 1, "batch_size": 32, "learning_rate": 0.001, "p_forall": 2, "p_exists": 2, "dropout_rate": 0.2, "size_val": 0.1, "accuracy": 0.0989999994635582, "model_file": "LTN_param_0_100_32_0.001_2_2_0.2_0.1"}
{"algorithm": "LTN", "seed": 0, "nb_epochs": 1, "batch_size": 128, "learning_rate": 0.001, "p_forall": 2, "p_exists": 2, "dropout_rate": 0.2, "size_val": 0.1, "accuracy": 0.0989999994635582, "model_file": "LTN_param_0_100_128_0.001_2_2_0.2_0.1"}
{"algorithm": "LTN", "seed": 0, "nb_epochs": 1, "batch_size": 512, "learning_rate": 0.001, "p_forall": 2, "p_exists": 2, "dropout_rate": 0.2, "size_val": 0.1, "accuracy": 0.0989999994635582, "model_file": "LTN_param_0_100_512_0.001_2_2_0.2_0.1"}
