{"algorithm": "LTN", "seed": 0, "nb_epochs_done": 1, "batch_size": 2, "learning_rate": 0.001, "p_forall": 1, "p_exists": 2, "p_forall_cites": 1, "p_exists_cites": 2, "dropout_rate": 0, "accuracy": 0.18799999356269836, "model_file": "LTN_param_0_1_2_0.001_1_2_1_2_0"}
{"algorithm": "LTN", "seed": 0, "nb_epochs_done": 2, "batch_size": 2, "learning_rate": 0.001, "p_forall": 1, "p_exists": 2, "p_forall_cites": 1, "p_exists_cites": 2, "dropout_rate": 0, "accuracy": 0.18799999356269836, "model_file": "LTN_param_0_2_2_0.001_1_2_1_2_0"}
{"algorithm": "LTN", "seed": 0, "nb_epochs_done": 3, "batch_size": 2, "learning_rate": 0.001, "p_forall": 1, "p_exists": 2, "p_forall_cites": 1, "p_exists_cites": 2, "dropout_rate": 0, "accuracy": 0.18799999356269836, "model_file": "LTN_param_0_3_2_0.001_1_2_1_2_0"}
